knack_sleuth/__init__.py
knack_sleuth/cli.py
knack_sleuth/config.py
knack_sleuth/core.py
knack_sleuth/db_schema.py
knack_sleuth/models.py
knack_sleuth/security.py
knack_sleuth/sleuth.py
knack_sleuth-0.2.4.dist-info/WHEEL
knack_sleuth-0.2.4.dist-info/entry_points.txt
knack_sleuth-0.2.4.dist-info/METADATA
knack_sleuth-0.2.4.dist-info/RECORD
