Metadata-Version: 2.3
Name: knack-sleuth
Version: 0.2.4
Summary: Investigate your Knack.app's metadata to find where data objects and fields are used throughout your application
Requires-Dist: httpx[http2]>=0.28.1
Requires-Dist: pydantic>=2.12.3
Requires-Dist: pydantic-settings>=2.11.0
Requires-Dist: pyyaml>=6.0.3
Requires-Dist: typer>=0.20.0
Requires-Python: >=3.13
Project-URL: Homepage, https://github.com/mcmasty/knack-sleuth
Project-URL: Issues, https://github.com/mcmasty/knack-sleuth/issues
Project-URL: Repository, https://github.com/mcmasty/knack-sleuth
